django_q_slack
