Metadata-Version: 2.1
Name: django-q-slack
Version: 0.2.0
Summary: A Slack support plugin for Django Q
Home-page: https://django-q.readthedocs.org
Author: Goran Vrbaški
Author-email: vrbaski.goran@gmail.com
License: MIT
Keywords: django distributed task queue worker scheduler cron redis disque ironmq sqs orm mongodb multiprocessing slack
Classifier: Programming Language :: Python :: 3
Classifier: License :: OSI Approved :: MIT License
Classifier: Operating System :: OS Independent
